setup.cfg
setup.py
tolib/__init__.py
tolib/tolib.py
tolib.egg-info/PKG-INFO
tolib.egg-info/SOURCES.txt
tolib.egg-info/dependency_links.txt
tolib.egg-info/not-zip-safe
tolib.egg-info/top_level.txt