Metadata-Version: 2.1
Name: tolib
Version: 1.1
Summary: Математический модуль
Author-email: tolibaevrinat4@gmail.com
